pycherwell/__init__.py
pycherwell/api_client.py
pycherwell/app_client.py
pycherwell/app_configuration.py
pycherwell/configuration.py
pycherwell/exceptions.py
pycherwell/rest.py
pycherwell/api/__init__.py
pycherwell/api/business_object_api.py
pycherwell/api/core_api.py
pycherwell/api/forms_api.py
pycherwell/api/queues_api.py
pycherwell/api/searches_api.py
pycherwell/api/security_api.py
pycherwell/api/service_api.py
pycherwell/api/teams_api.py
pycherwell/api/users_api.py
pycherwell/models/__init__.py
pycherwell/models/action.py
pycherwell/models/add_item_to_queue_request.py
pycherwell/models/add_item_to_queue_response.py
pycherwell/models/add_user_to_team_by_batch_request.py
pycherwell/models/add_user_to_team_by_batch_response.py
pycherwell/models/add_user_to_team_request.py
pycherwell/models/add_user_to_team_response.py
pycherwell/models/api_client_setting_response.py
pycherwell/models/association.py
pycherwell/models/attachment.py
pycherwell/models/attachments_request.py
pycherwell/models/attachments_response.py
pycherwell/models/barcode_lookup_response.py
pycherwell/models/batch_delete_request.py
pycherwell/models/batch_delete_response.py
pycherwell/models/batch_read_request.py
pycherwell/models/batch_read_response.py
pycherwell/models/batch_save_request.py
pycherwell/models/batch_save_response.py
pycherwell/models/bus_obs_for_view_response.py
pycherwell/models/business_object_permission.py
pycherwell/models/changed_limit.py
pycherwell/models/check_in_queue_item_request.py
pycherwell/models/check_in_queue_item_response.py
pycherwell/models/check_out_queue_item_request.py
pycherwell/models/check_out_queue_item_response.py
pycherwell/models/client_security_settings_response.py
pycherwell/models/delete_api_client_settings_response.py
pycherwell/models/delete_request.py
pycherwell/models/delete_response.py
pycherwell/models/export_search_results_request.py
pycherwell/models/field.py
pycherwell/models/field_definition.py
pycherwell/models/field_permission.py
pycherwell-1.0.9.dist-info/LICENSE.txt
pycherwell-1.0.9.dist-info/METADATA
pycherwell-1.0.9.dist-info/WHEEL
pycherwell-1.0.9.dist-info/top_level.txt
pycherwell-1.0.9.dist-info/RECORD
