Metadata-Version: 2.1
Name: pycherwell
Version: 1.0.9
Summary: Cherwell REST API Client and Library
Home-page: https://github.com/greenpau/pycherwell
Author: Paul Greenberg
Author-email: greenpau@outlook.com
License: UNKNOWN
Keywords: OpenAPI,OpenAPI-Generator,Cherwell REST API
Platform: UNKNOWN
Requires-Dist: urllib3 (>=1.15)
Requires-Dist: six (>=1.10)
Requires-Dist: certifi
Requires-Dist: python-dateutil
Requires-Dist: requests
